{
  "id": 2416,
  "title": "Boku wa Ookami.",
  "url": "https://mangadex.org/manga/2416",
  "last_updated": "January 17, 2021 06:40:34 UTC",
  "matches": [
    {
      "id": 7573,
      "title": "Seishun Trickers",
      "score": 0.754,
      "r18": false
    },
    {
      "id": 23967,
      "title": "Shinbunbu no Komatsu-san",
      "score": 0.753,
      "r18": false
    },
    {
      "id": 7516,
      "title": "Ai no Tame ni",
      "score": 0.73,
      "r18": false
    },
    {
      "id": 3650,
      "title": "Zettai Kareshi",
      "score": 0.719,
      "r18": false
    },
    {
      "id": 7481,
      "title": "Zenbu Chodai",
      "score": 0.715,
      "r18": false
    },
    {
      "id": 989,
      "title": "Gakuen Alice",
      "score": 0.711,
      "r18": false
    },
    {
      "id": 6862,
      "title": "Bokura wa Itsumo",
      "score": 0.708,
      "r18": false
    },
    {
      "id": 1371,
      "title": "Penguin Prince",
      "score": 0.707,
      "r18": false
    },
    {
      "id": 3076,
      "title": "Kanchigai Musume to Buchigire Ouji",
      "score": 0.707,
      "r18": false
    },
    {
      "id": 3381,
      "title": "Koi ni Naru Made",
      "score": 0.707,
      "r18": false
    },
    {
      "id": 28359,
      "title": "Boku ga Utau to Kimi wa Warau kara",
      "score": 0.704,
      "r18": false
    },
    {
      "id": 3082,
      "title": "Get Love!! ~Field no Ouji-sama~",
      "score": 0.703,
      "r18": false
    },
    {
      "id": 2450,
      "title": "I&rsquo;m Looking for the Princess",
      "score": 0.703,
      "r18": false
    },
    {
      "id": 3453,
      "title": "Hizamazuite Ai wo Chikae",
      "score": 0.702,
      "r18": false
    },
    {
      "id": 5362,
      "title": "Megane ~ Hazushitemo Iidesuka?",
      "score": 0.702,
      "r18": false
    },
    {
      "id": 4824,
      "title": "Rabu Kare - Gokujou Men Dokuhon!",
      "score": 0.701,
      "r18": false
    },
    {
      "id": 3159,
      "title": "Kataomoi no Mukougawa",
      "score": 0.701,
      "r18": false
    },
    {
      "id": 13685,
      "title": "Watashi no Ookami-kun",
      "score": 0.701,
      "r18": false
    },
    {
      "id": 174,
      "title": "Forget About Love",
      "score": 0.7,
      "r18": false
    },
    {
      "id": 17089,
      "title": "Sakuragaoka Angels",
      "score": 0.7,
      "r18": false
    },
    {
      "id": 2683,
      "title": "Hatsumei Princess",
      "score": 0.699,
      "r18": false
    },
    {
      "id": 6082,
      "title": "Yume Miru Happa",
      "score": 0.699,
      "r18": false
    },
    {
      "id": 1899,
      "title": "His and Her Circumstances",
      "score": 0.699,
      "r18": false
    },
    {
      "id": 7372,
      "title": "NG BOY x Paradise",
      "score": 0.697,
      "r18": false
    },
    {
      "id": 4175,
      "title": "Cream Caramel Chocolate",
      "score": 0.696,
      "r18": false
    }
  ]
}