{
  "id": 3217,
  "title": "Seitoshidoushitsu no Ouji-sama",
  "url": "https://mangadex.org/manga/3217",
  "description": "Kanbara Rinko is a half-Japanese, half-British girl, so she has blonde hair and blue eyes. However, the vice president of the public moral committee at her school, Kotoshiba, thinks that she dyed her hair and uses contact lenses, so he constantly gives her troubles. And with her attitude, everyone in her class thinks that she&rsquo;s a delinquent, so she doesn&rsquo;t have any friends. Her only joy in coming to school is to see Hachiouji-senpai, the gentle and handsome president of the public moral committee. She thinks he&rsquo;s her ideal prince, but is he really?",
  "is_r18": false,
  "rating": 7.92,
  "demographic": [
    "Shoujo"
  ],
  "content": [],
  "format": [
    "Oneshot"
  ],
  "genre": [
    "Romance"
  ],
  "theme": [
    "School Life"
  ],
  "languages": [
    "gb"
  ],
  "related": [],
  "external": {
    "al": "41654",
    "ap": "seitoshidoushitsu-no-ouji-sama",
    "kt": "21734",
    "mu": "39761",
    "mal": "11654"
  },
  "last_updated": "March 18, 2021 06:10:45 UTC",
  "matches": [
    {
      "id": 18104,
      "title": "Spring One Year Later",
      "score": 0.361,
      "r18": false,
      "languages": [
        "gb"
      ]
    },
    {
      "id": 2394,
      "title": "Okitsune no Hanayome",
      "score": 0.361,
      "r18": false,
      "languages": [
        "gb"
      ]
    },
    {
      "id": 4579,
      "title": "Mask Catharsis",
      "score": 0.357,
      "r18": false,
      "languages": [
        "gb"
      ]
    },
    {
      "id": 14861,
      "title": "Sakashita-senpai no Koigokoro",
      "score": 0.357,
      "r18": false,
      "languages": [
        "br",
        "pl",
        "gb"
      ]
    },
    {
      "id": 35081,
      "title": "Love Period",
      "score": 0.354,
      "r18": false,
      "languages": [
        "gb",
        "mx"
      ]
    },
    {
      "id": 45402,
      "title": "Momoten Musume",
      "score": 0.352,
      "r18": false,
      "languages": [
        "gb"
      ]
    },
    {
      "id": 16643,
      "title": "Navy Blue no Hoshizora",
      "score": 0.351,
      "r18": false,
      "languages": [
        "gb"
      ]
    },
    {
      "id": 3076,
      "title": "Kanchigai Musume to Buchigire Ouji",
      "score": 0.351,
      "r18": false,
      "languages": [
        "gb"
      ]
    },
    {
      "id": 4635,
      "title": "Aka no Yuuwaku",
      "score": 0.351,
      "r18": false,
      "languages": [
        "ph",
        "gb"
      ]
    },
    {
      "id": 3178,
      "title": "Hana to Watashi",
      "score": 0.35,
      "r18": false,
      "languages": [
        "gb"
      ]
    },
    {
      "id": 14755,
      "title": "Kare no Iinari",
      "score": 0.35,
      "r18": false,
      "languages": [
        "gb"
      ]
    },
    {
      "id": 10376,
      "title": "Kiss Tokidoki Kiss Tokoro ni Yori Kiss",
      "score": 0.35,
      "r18": false,
      "languages": [
        "gb"
      ]
    },
    {
      "id": 4259,
      "title": "Onkochisin na Kanojo",
      "score": 0.35,
      "r18": false,
      "languages": [
        "gb"
      ]
    },
    {
      "id": 17424,
      "title": "Senaka no Otoko",
      "score": 0.35,
      "r18": false,
      "languages": [
        "gb"
      ]
    },
    {
      "id": 14588,
      "title": "Cinderella Lesson",
      "score": 0.35,
      "r18": false,
      "languages": [
        "gb"
      ]
    },
    {
      "id": 14714,
      "title": "Yorimichi :RE",
      "score": 0.35,
      "r18": false,
      "languages": [
        "gb"
      ]
    },
    {
      "id": 6790,
      "title": "Kuraku naru Made Matte",
      "score": 0.35,
      "r18": false,
      "languages": [
        "gb"
      ]
    },
    {
      "id": 10615,
      "title": "Land Escape",
      "score": 0.35,
      "r18": false,
      "languages": [
        "gb"
      ]
    },
    {
      "id": 29347,
      "title": "Kimi to Watashii no Taiiku no Jikan",
      "score": 0.35,
      "r18": false,
      "languages": [
        "es",
        "gb"
      ]
    },
    {
      "id": 3177,
      "title": "Hana Sakasu Te",
      "score": 0.35,
      "r18": false,
      "languages": [
        "gb",
        "bg"
      ]
    },
    {
      "id": 32497,
      "title": "Hajimete no Koi no Sodatekata",
      "score": 0.35,
      "r18": false,
      "languages": [
        "gb"
      ]
    },
    {
      "id": 20278,
      "title": "Kimi to Houkago. (Haru Aoi)",
      "score": 0.35,
      "r18": false,
      "languages": [
        "gb",
        "br",
        "es"
      ]
    },
    {
      "id": 28580,
      "title": "Reversi",
      "score": 0.35,
      "r18": false,
      "languages": [
        "gb",
        "br"
      ]
    },
    {
      "id": 45983,
      "title": "Daruma no Kokoro",
      "score": 0.35,
      "r18": false,
      "languages": [
        "gb"
      ]
    },
    {
      "id": 11073,
      "title": "Suki ni Natta yo",
      "score": 0.35,
      "r18": false,
      "languages": [
        "gb"
      ]
    }
  ]
}