{
  "id": 6957,
  "title": "Love Automation",
  "url": "https://mangadex.org/manga/6957",
  "last_updated": "January 17, 2021 18:53:47 UTC",
  "matches": [
    {
      "id": 7142,
      "title": "FamiDol!",
      "score": 0.731,
      "r18": false
    },
    {
      "id": 19496,
      "title": "Her Love is so heavy, it hurts.",
      "score": 0.687,
      "r18": false
    },
    {
      "id": 978,
      "title": "Boku no Idol",
      "score": 0.685,
      "r18": false
    },
    {
      "id": 36633,
      "title": "To Love-Ru - Kentaro Yabuki 20th Anniversary",
      "score": 0.666,
      "r18": false
    },
    {
      "id": 43518,
      "title": "I Want to See a Naked Girl in Real Life",
      "score": 0.663,
      "r18": false
    },
    {
      "id": 17070,
      "title": "Nanai Sanami ga Kiratte Kurenai",
      "score": 0.661,
      "r18": false
    },
    {
      "id": 1573,
      "title": "Princess School",
      "score": 0.655,
      "r18": false
    },
    {
      "id": 3898,
      "title": "Koi no Dracula",
      "score": 0.484,
      "r18": false
    },
    {
      "id": 18897,
      "title": "Gachipin.",
      "score": 0.41,
      "r18": false
    },
    {
      "id": 3897,
      "title": "Takidani Koukou Manga Club",
      "score": 0.41,
      "r18": false
    },
    {
      "id": 2050,
      "title": "Hakui no Kanojo",
      "score": 0.394,
      "r18": false
    },
    {
      "id": 11322,
      "title": "Onaidoshi no Onee-san",
      "score": 0.39,
      "r18": false
    },
    {
      "id": 14203,
      "title": "Nekonotemo",
      "score": 0.366,
      "r18": false
    },
    {
      "id": 726,
      "title": "Futagami Double",
      "score": 0.342,
      "r18": false
    },
    {
      "id": 16679,
      "title": "Gakuen Dragon Slayer",
      "score": 0.309,
      "r18": false
    },
    {
      "id": 20481,
      "title": "Haruyo, Koi!",
      "score": 0.307,
      "r18": false
    },
    {
      "id": 12296,
      "title": "Swimsuit World",
      "score": 0.298,
      "r18": false
    },
    {
      "id": 40766,
      "title": "Gal Kazoku",
      "score": 0.294,
      "r18": false
    },
    {
      "id": 8720,
      "title": "Sakuran (IWASHIRO Toshiaki)",
      "score": 0.273,
      "r18": false
    },
    {
      "id": 10383,
      "title": "Tackle Shoujo",
      "score": 0.272,
      "r18": false
    },
    {
      "id": 46681,
      "title": "Morning Routine of Couples in Action Manga",
      "score": 0.272,
      "r18": false
    },
    {
      "id": 50031,
      "title": "A Story of a Senpai, Who Is Proud of Her Swimsuit Because She Thinks It Looks Cool",
      "score": 0.272,
      "r18": false
    },
    {
      "id": 19548,
      "title": "Uchuuji Karabuki Kenzan",
      "score": 0.22,
      "r18": false
    },
    {
      "id": 679,
      "title": "Doki Doki Summer Beach",
      "score": 0.194,
      "r18": false
    },
    {
      "id": 5596,
      "title": "Akiiro Bousou Biyori",
      "score": 0.194,
      "r18": false
    }
  ]
}