{
  "id": 11261,
  "title": "Toriaezu Chikyuu Ga Horobiru Mae Ni",
  "url": "https://mangadex.org/manga/11261",
  "last_updated": "January 18, 2021 06:57:16 UTC",
  "matches": [
    {
      "id": 3300,
      "title": "Kuraku Naru Made Matenai",
      "score": 0.397,
      "r18": false
    },
    {
      "id": 3422,
      "title": "Kimi no Tame ni Hiku Chopin",
      "score": 0.394,
      "r18": false
    },
    {
      "id": 2033,
      "title": "Barairo My Honey",
      "score": 0.388,
      "r18": false
    },
    {
      "id": 34345,
      "title": "Shizuko wa Ore no Yome",
      "score": 0.38,
      "r18": false
    },
    {
      "id": 53720,
      "title": "Koko kara wa Otona no Jikan desu.",
      "score": 0.374,
      "r18": false
    },
    {
      "id": 15751,
      "title": "Ginban Kishi",
      "score": 0.372,
      "r18": false
    },
    {
      "id": 21563,
      "title": "Ookami Koushaku no Kyuukon",
      "score": 0.371,
      "r18": false
    },
    {
      "id": 17398,
      "title": "Daidai Boshi",
      "score": 0.347,
      "r18": false
    },
    {
      "id": 15707,
      "title": "Koudaike no Hitobito",
      "score": 0.347,
      "r18": false
    },
    {
      "id": 4442,
      "title": "Arcana 04 - Vampire",
      "score": 0.338,
      "r18": false
    },
    {
      "id": 15601,
      "title": "Happy if You Died",
      "score": 0.335,
      "r18": false
    },
    {
      "id": 8952,
      "title": "Ketchup Mayonnaise",
      "score": 0.331,
      "r18": false
    },
    {
      "id": 48692,
      "title": "Heir to the Cabbage Patch",
      "score": 0.327,
      "r18": false
    },
    {
      "id": 6444,
      "title": "Saikyou no Tenshi Nishite Saiai no Akuma",
      "score": 0.326,
      "r18": false
    },
    {
      "id": 7547,
      "title": "Anata ga Ireba",
      "score": 0.322,
      "r18": false
    },
    {
      "id": 49752,
      "title": "Kijima-san to Yamada-san",
      "score": 0.293,
      "r18": false
    },
    {
      "id": 58145,
      "title": "Kuuki ga &quot;Yomeru&quot; Shinnyushain to Buaiso na Senpai no Hanashi (Serialization)",
      "score": 0.292,
      "r18": false
    },
    {
      "id": 2558,
      "title": "Machi de Uwasa no Tengu no Ko",
      "score": 0.29,
      "r18": false
    },
    {
      "id": 36256,
      "title": "Iwakutsuki Bukken no Yakuro-san",
      "score": 0.281,
      "r18": false
    },
    {
      "id": 1063,
      "title": "Chihayafuru",
      "score": 0.277,
      "r18": false
    },
    {
      "id": 28531,
      "title": "Ao no Haha",
      "score": 0.277,
      "r18": false
    },
    {
      "id": 33982,
      "title": "The Matchmaker Forbids Me From Dating",
      "score": 0.272,
      "r18": false
    },
    {
      "id": 58870,
      "title": "My Butler, Not Lover",
      "score": 0.266,
      "r18": false
    },
    {
      "id": 57560,
      "title": "The Flower Doll and her Husband",
      "score": 0.259,
      "r18": false
    },
    {
      "id": 6093,
      "title": "Saiyuki RELOAD",
      "score": 0.258,
      "r18": false
    }
  ]
}