{
  "id": 12796,
  "title": "JC no Life",
  "url": "https://mangadex.org/manga/12796",
  "last_updated": "March 18, 2021 07:34:57 UTC",
  "matches": [
    {
      "id": 5499,
      "title": "Mitsudomoe",
      "score": 0.24,
      "r18": false,
      "languages": [
        "gb"
      ]
    },
    {
      "id": 8345,
      "title": "Chichi ga Loli na Mono de",
      "score": 0.24,
      "r18": false,
      "languages": [
        "gb",
        "br"
      ]
    },
    {
      "id": 240,
      "title": "Ichinensei ni Nacchattara",
      "score": 0.2,
      "r18": false,
      "languages": [
        "gb"
      ]
    },
    {
      "id": 26310,
      "title": "Waga Itoshi no Wota Kanojo",
      "score": 0.2,
      "r18": false,
      "languages": [
        "gb",
        "fr",
        "id"
      ]
    },
    {
      "id": 544,
      "title": "Tonari no Randoseru W",
      "score": 0.171,
      "r18": false,
      "languages": [
        "gb"
      ]
    },
    {
      "id": 22996,
      "title": "Rororro!",
      "score": 0.171,
      "r18": false,
      "languages": [
        "gb",
        "it"
      ]
    },
    {
      "id": 49639,
      "title": "Alice no Hanamuko",
      "score": 0.15,
      "r18": false,
      "languages": [
        "gb"
      ]
    },
    {
      "id": 41006,
      "title": "Kagekuri Kitan",
      "score": 0.133,
      "r18": false,
      "languages": [
        "hk",
        "gb",
        "mx",
        "ru"
      ]
    }
  ]
}