{
  "id": 13720,
  "title": "Kono Subarashii Sekai ni Shukufuku wo!",
  "url": "https://api.mangadex.org/v2/manga/13720",
  "last_updated": "February 08, 2021 08:38:23 UTC",
  "matches": [
    {
      "id": 28735,
      "title": "Isekai Shoukan wa Nidome Desu",
      "score": 0.758,
      "r18": false
    },
    {
      "id": 15950,
      "title": "Isekai Maou to Shoukan Shoujo no Dorei Majutsu",
      "score": 0.758,
      "r18": false
    },
    {
      "id": 5552,
      "title": "Campione!",
      "score": 0.743,
      "r18": false
    },
    {
      "id": 3507,
      "title": "Megu Miruku",
      "score": 0.742,
      "r18": false
    },
    {
      "id": 6,
      "title": "Shijou Saikyou no Deshi Kenichi",
      "score": 0.741,
      "r18": false
    },
    {
      "id": 86,
      "title": "Anedoki",
      "score": 0.741,
      "r18": false
    },
    {
      "id": 1882,
      "title": "Baka to Test to Shoukanjuu",
      "score": 0.739,
      "r18": false
    },
    {
      "id": 971,
      "title": "Maga-Tsuki",
      "score": 0.737,
      "r18": false
    },
    {
      "id": 14458,
      "title": "Magical P&acirc;tissi&egrave;re Kosaki-chan!!",
      "score": 0.737,
      "r18": false
    },
    {
      "id": 55481,
      "title": "A Sword Master Childhood Friend Power Harassed Me Harshly, so I Broke off Our Relationship and Made a Fresh Start at the Frontier as a Magic Swordsman",
      "score": 0.736,
      "r18": false
    },
    {
      "id": 9855,
      "title": "Shinigami-sama to 4-nin no Kanojo",
      "score": 0.736,
      "r18": false
    },
    {
      "id": 31349,
      "title": "Dungeon ni Deai o Motomeru no wa Machigatte Iru Darou ka (Fan Colored)",
      "score": 0.735,
      "r18": false
    },
    {
      "id": 4906,
      "title": "MuvLuv Unlimited",
      "score": 0.734,
      "r18": false
    },
    {
      "id": 2404,
      "title": "Love Hina",
      "score": 0.734,
      "r18": false
    },
    {
      "id": 1391,
      "title": "Loose Relation Between Wizard &amp; Apprentice",
      "score": 0.733,
      "r18": false
    },
    {
      "id": 1062,
      "title": "Shina Dark ~Kuroki Tsuki no Ou to Souheiki no Himegimi~",
      "score": 0.733,
      "r18": false
    },
    {
      "id": 6138,
      "title": "Full Metal Panic!",
      "score": 0.732,
      "r18": false
    },
    {
      "id": 25332,
      "title": "Hiota no Kanojo ga Ore no Motteru Eroge ni Kyoumi Shinshin Nanda ga......",
      "score": 0.731,
      "r18": false
    },
    {
      "id": 9175,
      "title": "Shinmai Maou no Testament",
      "score": 0.73,
      "r18": false
    },
    {
      "id": 29672,
      "title": "Ore Dake Haireru Kakushi Dungeon: Kossori Kitaete Sekai Saikyou",
      "score": 0.73,
      "r18": false
    },
    {
      "id": 38972,
      "title": "The Middle-aged Man Who Just Returned From Another World Melts His Fathercon Daughters With His Paternal Skill",
      "score": 0.73,
      "r18": false
    },
    {
      "id": 30,
      "title": "Sora no Otoshimono",
      "score": 0.729,
      "r18": false
    },
    {
      "id": 14472,
      "title": "Busou Shoujo Machiavellism",
      "score": 0.729,
      "r18": false
    },
    {
      "id": 5327,
      "title": "Tora Kiss - A School Odyssey",
      "score": 0.729,
      "r18": false
    },
    {
      "id": 2646,
      "title": "Mushibugyo",
      "score": 0.728,
      "r18": false
    }
  ]
}