{
  "id": 16253,
  "title": "The Song of the Beast",
  "url": "https://mangadex.org/manga/16253",
  "description": "An oriental fantasy manhwa that spans between Earth and the Underworld, using re-interpreted Korean myths and legends!",
  "is_r18": false,
  "rating": 0,
  "demographic": [],
  "content": [],
  "format": [
    "Long Strip"
  ],
  "genre": [
    "Action",
    "Adventure",
    "Comedy",
    "Fantasy"
  ],
  "theme": [],
  "languages": [
    "gb"
  ],
  "related": [],
  "external": {
    "ap": "the-song-of-the-beast",
    "mu": "125717"
  },
  "last_updated": "March 18, 2021 08:06:46 UTC",
  "matches": [
    {
      "id": 28998,
      "title": "Birth of Evil",
      "score": 0.35,
      "r18": false,
      "languages": [
        "gb"
      ]
    },
    {
      "id": 26818,
      "title": "Limbless Schira",
      "score": 0.291,
      "r18": false,
      "languages": [
        "gb",
        "tr",
        "sa",
        "id"
      ]
    },
    {
      "id": 49718,
      "title": "The Descent of the Spiritual Deity",
      "score": 0.291,
      "r18": false,
      "languages": [
        "gb",
        "br",
        "fr"
      ]
    },
    {
      "id": 10248,
      "title": "Fable",
      "score": 0.291,
      "r18": false,
      "languages": [
        "gb",
        "pl",
        "fr"
      ]
    },
    {
      "id": 10610,
      "title": "Dragon Recipe",
      "score": 0.291,
      "r18": false,
      "languages": [
        "gb",
        "pl",
        "mx",
        "br"
      ]
    },
    {
      "id": 18534,
      "title": "Wizardly Tower",
      "score": 0.291,
      "r18": false,
      "languages": [
        "fr",
        "gb",
        "mx",
        "br"
      ]
    },
    {
      "id": 4021,
      "title": "Son Yeon Jeon [Limit]",
      "score": 0.291,
      "r18": false,
      "languages": [
        "gb"
      ]
    },
    {
      "id": 18143,
      "title": "Romsen Saga",
      "score": 0.279,
      "r18": false,
      "languages": [
        "gb",
        "ru"
      ]
    },
    {
      "id": 16015,
      "title": "Fairy Tail Gaiden - Kengami no Souryuu",
      "score": 0.279,
      "r18": false,
      "languages": [
        "es",
        "gb",
        "it"
      ]
    },
    {
      "id": 8660,
      "title": "Shinpi no Sekai - El-Hazard",
      "score": 0.279,
      "r18": false,
      "languages": [
        "gb",
        "fr"
      ]
    },
    {
      "id": 30509,
      "title": "Eiyuu Densetsu - Sen no Kiseki IV",
      "score": 0.279,
      "r18": false,
      "languages": [
        "gb"
      ]
    },
    {
      "id": 34156,
      "title": "Won't There Be a Problem If The Hero Is Such a Horrible Person?",
      "score": 0.279,
      "r18": false,
      "languages": [
        "gb"
      ]
    },
    {
      "id": 24327,
      "title": "Zelda no Densetsu - 4-tsu no Tsurugi +",
      "score": 0.279,
      "r18": false,
      "languages": [
        "gb"
      ]
    },
    {
      "id": 24230,
      "title": "World of Cultivation",
      "score": 0.279,
      "r18": false,
      "languages": [
        "gb"
      ]
    },
    {
      "id": 24120,
      "title": "I am a Great God",
      "score": 0.279,
      "r18": false,
      "languages": [
        "gb",
        "tr",
        "fr",
        "id",
        "ru"
      ]
    },
    {
      "id": 21559,
      "title": "Digimon Chronicle",
      "score": 0.279,
      "r18": false,
      "languages": [
        "fr",
        "gb",
        "br"
      ]
    },
    {
      "id": 25450,
      "title": "Zelda no Densetsu - Mugen no Sunadokei",
      "score": 0.279,
      "r18": false,
      "languages": [
        "gb"
      ]
    },
    {
      "id": 18907,
      "title": "Dawn of the Eastland",
      "score": 0.279,
      "r18": false,
      "languages": [
        "gb",
        "fr",
        "tr"
      ]
    },
    {
      "id": 2260,
      "title": "Dokkan Love",
      "score": 0.279,
      "r18": false,
      "languages": [
        "gb"
      ]
    },
    {
      "id": 23721,
      "title": "Memesis",
      "score": 0.279,
      "r18": false,
      "languages": [
        "ru",
        "de",
        "es",
        "gb"
      ]
    },
    {
      "id": 39414,
      "title": "100-nin no Eiyuu o Sodateta Saikyou Yogensha wa, Boukensha ni Natte mo Sekaijuu no Deshi kara Shitawarete Masu",
      "score": 0.279,
      "r18": false,
      "languages": [
        "gb",
        "id",
        "mx",
        "br",
        "ru",
        "es",
        "fr"
      ]
    },
    {
      "id": 24599,
      "title": "Lunar - Tsuki no Kokuhaku",
      "score": 0.279,
      "r18": false,
      "languages": [
        "gb"
      ]
    },
    {
      "id": 6733,
      "title": "Full Ahead! Coco",
      "score": 0.279,
      "r18": false,
      "languages": [
        "gb",
        "mx",
        "it"
      ]
    },
    {
      "id": 5044,
      "title": "Trace: Perfume",
      "score": 0.279,
      "r18": false,
      "languages": [
        "gb"
      ]
    },
    {
      "id": 29587,
      "title": "Full Ahead! Coco Zervance",
      "score": 0.279,
      "r18": false,
      "languages": [
        "gb"
      ]
    }
  ]
}