{
  "id": 29022,
  "title": "Kunshu no Ai wa Yoru ni Hana Saku",
  "url": "https://mangadex.org/manga/29022",
  "last_updated": "December 23, 2020 06:38:12 UTC",
  "matches": [
    {
      "id": 24621,
      "title": "Amaiyo Maiyo",
      "score": 0.832
    },
    {
      "id": 53590,
      "title": "Mikansei na Karada",
      "score": 0.832
    },
    {
      "id": 37504,
      "title": "Hide and Seek",
      "score": 0.826
    },
    {
      "id": 57214,
      "title": "Damatte Naite Irunodesu",
      "score": 0.82
    },
    {
      "id": 28360,
      "title": "Boku no Kawaii Hito",
      "score": 0.82
    },
    {
      "id": 27684,
      "title": "Yokubou Shounen",
      "score": 0.816
    },
    {
      "id": 57212,
      "title": "Hey! Doctor",
      "score": 0.815
    },
    {
      "id": 27807,
      "title": "Taka wo Kukurouka",
      "score": 0.814
    },
    {
      "id": 25954,
      "title": "Natsukoi",
      "score": 0.805
    },
    {
      "id": 29020,
      "title": "Koibito wa Hatsujouki",
      "score": 0.801
    },
    {
      "id": 36991,
      "title": "Nemureru Kimi no Barairo no Kuchibiru",
      "score": 0.8
    },
    {
      "id": 50437,
      "title": "Dokusenyoku",
      "score": 0.799
    },
    {
      "id": 35741,
      "title": "Chouhatsu - Denkou Sekka Boys",
      "score": 0.797
    },
    {
      "id": 37352,
      "title": "Kohitsuji to Ookami",
      "score": 0.795
    },
    {
      "id": 57336,
      "title": "Ai wa Karada de Kataru Mono",
      "score": 0.792
    },
    {
      "id": 24607,
      "title": "Kimi de Oboreta Ato wa",
      "score": 0.791
    },
    {
      "id": 37735,
      "title": "Harem de Hitori",
      "score": 0.79
    },
    {
      "id": 12021,
      "title": "Wild Darling",
      "score": 0.783
    },
    {
      "id": 13046,
      "title": "Kami-sama no Ude no Naka",
      "score": 0.781
    },
    {
      "id": 4557,
      "title": "Mousou Cherry",
      "score": 0.781
    },
    {
      "id": 51148,
      "title": "Kaikan Fortune",
      "score": 0.78
    },
    {
      "id": 55840,
      "title": "Ijimetai hodo Aishiteru",
      "score": 0.776
    },
    {
      "id": 4118,
      "title": "Kimi Note",
      "score": 0.775
    },
    {
      "id": 3982,
      "title": "Only One",
      "score": 0.774
    },
    {
      "id": 38928,
      "title": "Aisubeki Fujitsu",
      "score": 0.773
    }
  ]
}