{
  "id": 43142,
  "title": "Jikobukken no Yuurei-chan",
  "url": "https://mangadex.org/manga/43142",
  "last_updated": "January 15, 2021 01:44:46 UTC",
  "matches": [
    {
      "id": 3757,
      "title": "Youkai Apaato no Yuuga na Nichijou",
      "score": 0.419
    },
    {
      "id": 57602,
      "title": "Zashiki Musume to Ryourinin",
      "score": 0.398
    },
    {
      "id": 23944,
      "title": "REIGEN",
      "score": 0.395
    },
    {
      "id": 8587,
      "title": "Neko Ane",
      "score": 0.387
    },
    {
      "id": 27107,
      "title": "Obake Monogatari",
      "score": 0.384
    },
    {
      "id": 13434,
      "title": "Uchi no Maou Kamimasen yo",
      "score": 0.379
    },
    {
      "id": 49304,
      "title": "Apartment Ghost",
      "score": 0.377
    },
    {
      "id": 20351,
      "title": "Kabe ni Mary.com",
      "score": 0.376
    },
    {
      "id": 9802,
      "title": "Maou no Kyoushitsu",
      "score": 0.372
    },
    {
      "id": 6133,
      "title": "The Time of Cherry Blossoms",
      "score": 0.367
    },
    {
      "id": 21892,
      "title": "Hakui no Ou-sama",
      "score": 0.363
    },
    {
      "id": 27870,
      "title": "Yajin",
      "score": 0.361
    },
    {
      "id": 15169,
      "title": "Nanoha Yougashiten no Ii Shigoto",
      "score": 0.359
    },
    {
      "id": 17005,
      "title": "Kiitarou Shounen no Youkai Enikki",
      "score": 0.357
    },
    {
      "id": 343,
      "title": "Shinryaku! Ika Musume",
      "score": 0.356
    },
    {
      "id": 21513,
      "title": "Sodatechi Maou!",
      "score": 0.353
    },
    {
      "id": 13005,
      "title": "Hyakka no Shirushi",
      "score": 0.351
    },
    {
      "id": 1291,
      "title": "Itsumo Misora",
      "score": 0.349
    },
    {
      "id": 51607,
      "title": "Kyouka-sama no sweet sweet boro house",
      "score": 0.347
    },
    {
      "id": 42460,
      "title": "Obake no Q-Taro",
      "score": 0.344
    },
    {
      "id": 2913,
      "title": "Tokyo Innocent",
      "score": 0.342
    },
    {
      "id": 7102,
      "title": "Momomoke Restaurant",
      "score": 0.341
    },
    {
      "id": 876,
      "title": "Mononokemono",
      "score": 0.34
    },
    {
      "id": 43111,
      "title": "I Am Their Catships' Catservant",
      "score": 0.339
    },
    {
      "id": 1406,
      "title": "Noritama",
      "score": 0.337
    }
  ]
}