{
  "id": 44234,
  "title": "Satsuriku no Kuindeddo &ndash; 7-nin no Onna Shikeishuu",
  "url": "https://mangadex.org/manga/44234",
  "description": "Death row prisoner. Criminals who committed violent crimes and were sentenced to death by law. Akari, a woman who had no meaning in the prison island &ldquo;Deep Palace&rdquo; near death, accommodating them, acted with a certain purpose. Just when she thought she was able to complete my purpose safely, the death row prisoners has started to kill each other? A battle royal &ldquo;Killing&rdquo; was held where men and women were separated and the remaining team could escape!! Can Akari survive the &ldquo;Killing&rdquo; safely and escape from prison? Blood, Eros, and dangerous guys fly around, all the characters, a Battle Royale of all scum prisoners!!!!!",
  "is_r18": false,
  "rating": 7.11,
  "demographic": [],
  "content": [
    "Ecchi"
  ],
  "format": [],
  "genre": [
    "Action",
    "Drama",
    "Horror"
  ],
  "theme": [
    "Crossdressing"
  ],
  "languages": [
    "mx",
    "gb"
  ],
  "related": [],
  "external": {
    "mu": "160427"
  },
  "last_updated": "March 18, 2021 12:29:40 UTC",
  "matches": []
}