{
  "id": 53293,
  "title": "Succubus Okotowari",
  "url": "https://mangadex.org/manga/53293",
  "last_updated": "January 16, 2021 01:04:53 UTC",
  "matches": [
    {
      "id": 32893,
      "title": "Shachiku Succubus no Hanashi",
      "score": 0.728
    },
    {
      "id": 38480,
      "title": "Shachiku Succubus no Hanashi (Fan Colored)",
      "score": 0.725
    },
    {
      "id": 41088,
      "title": "Koibito wa Oni no Hime",
      "score": 0.659
    },
    {
      "id": 809,
      "title": "Maji Bura!?",
      "score": 0.354
    },
    {
      "id": 56047,
      "title": "Doki Doki Yokai Love Battle! ~ Great Yokai War!",
      "score": 0.354
    },
    {
      "id": 1391,
      "title": "Loose Relation Between Wizard &amp; Apprentice",
      "score": 0.319
    },
    {
      "id": 6242,
      "title": "Hataraku Maou-sama! High School!",
      "score": 0.318
    },
    {
      "id": 29306,
      "title": "Sore wa Tada no Senpai no Chinko",
      "score": 0.316
    },
    {
      "id": 19488,
      "title": "Oroka na Tenshi wa Akuma to Odoru",
      "score": 0.314
    },
    {
      "id": 47683,
      "title": "The Three Sisters Are Trying To Seduce Me!!",
      "score": 0.311
    },
    {
      "id": 732,
      "title": "To Love-Ru",
      "score": 0.308
    },
    {
      "id": 41070,
      "title": "Oversized Sextet",
      "score": 0.305
    },
    {
      "id": 1224,
      "title": "Perowan! - Hayaku Shinasai! Goshujinsama",
      "score": 0.305
    },
    {
      "id": 659,
      "title": "Kaibutsu Oujo",
      "score": 0.305
    },
    {
      "id": 23256,
      "title": "Urushiha Sarara wa Koi Nado Shinai",
      "score": 0.304
    },
    {
      "id": 22651,
      "title": "Jingai no Yome to Icha Icha suru - Anthology Comic",
      "score": 0.304
    },
    {
      "id": 60,
      "title": "Enchanter",
      "score": 0.3
    },
    {
      "id": 26030,
      "title": "Asmodeus wa Akiramenai",
      "score": 0.294
    },
    {
      "id": 21092,
      "title": "Devilchi",
      "score": 0.293
    },
    {
      "id": 3678,
      "title": "Enma no Hanayome to Kimetsukerareta Fukou na Ore no Jinsei Keikaku",
      "score": 0.291
    },
    {
      "id": 55284,
      "title": "Gahi-chan!",
      "score": 0.29
    },
    {
      "id": 5552,
      "title": "Campione!",
      "score": 0.286
    },
    {
      "id": 17891,
      "title": "Hyulla's Clan",
      "score": 0.284
    },
    {
      "id": 561,
      "title": "Onihime VS",
      "score": 0.284
    },
    {
      "id": 57,
      "title": "Carnivorous Princess Yegrinna",
      "score": 0.28
    }
  ]
}