{
  "id": 59406,
  "title": "Secret Love (Pre-Serialization)",
  "url": "https://api.mangadex.org/v2/manga/59406",
  "last_updated": "February 06, 2021 08:26:50 UTC",
  "matches": [
    {
      "id": 7181,
      "title": "Seishun Survival",
      "score": 0.716,
      "r18": false
    },
    {
      "id": 1371,
      "title": "Penguin Prince",
      "score": 0.714,
      "r18": false
    },
    {
      "id": 4824,
      "title": "Rabu Kare - Gokujou Men Dokuhon!",
      "score": 0.713,
      "r18": false
    },
    {
      "id": 2789,
      "title": "GIRL",
      "score": 0.713,
      "r18": false
    },
    {
      "id": 174,
      "title": "Forget About Love",
      "score": 0.71,
      "r18": false
    },
    {
      "id": 5855,
      "title": "Cream Caramel",
      "score": 0.709,
      "r18": false
    },
    {
      "id": 4175,
      "title": "Cream Caramel Chocolate",
      "score": 0.709,
      "r18": false
    },
    {
      "id": 2202,
      "title": "Lovely\u2605Complex",
      "score": 0.708,
      "r18": false
    },
    {
      "id": 3082,
      "title": "Get Love!! ~Field no Ouji-sama~",
      "score": 0.707,
      "r18": false
    },
    {
      "id": 52958,
      "title": "I&rsquo;m the Villainess, but the Capture Targets Are Too Abnormal",
      "score": 0.706,
      "r18": false
    },
    {
      "id": 3076,
      "title": "Kanchigai Musume to Buchigire Ouji",
      "score": 0.705,
      "r18": false
    },
    {
      "id": 6515,
      "title": "Himikoi",
      "score": 0.704,
      "r18": false
    },
    {
      "id": 23013,
      "title": "The Vengeful White Cat Lounging on the Dragon King's Lap",
      "score": 0.704,
      "r18": false
    },
    {
      "id": 8527,
      "title": "Akaiito",
      "score": 0.703,
      "r18": false
    },
    {
      "id": 3453,
      "title": "Hizamazuite Ai wo Chikae",
      "score": 0.703,
      "r18": false
    },
    {
      "id": 2683,
      "title": "Hatsumei Princess",
      "score": 0.703,
      "r18": false
    },
    {
      "id": 11867,
      "title": "Hotarubi no Mori e",
      "score": 0.702,
      "r18": false
    },
    {
      "id": 40745,
      "title": "Flowers in the Secret Place",
      "score": 0.7,
      "r18": false
    },
    {
      "id": 4085,
      "title": "Tig-Hug Planet",
      "score": 0.7,
      "r18": false
    },
    {
      "id": 49338,
      "title": "I Just Want to Be a Useless Duke's Daughter",
      "score": 0.7,
      "r18": false
    },
    {
      "id": 51626,
      "title": "The Lady's Butler",
      "score": 0.7,
      "r18": false
    },
    {
      "id": 28359,
      "title": "Boku ga Utau to Kimi wa Warau kara",
      "score": 0.698,
      "r18": false
    },
    {
      "id": 6082,
      "title": "Yume Miru Happa",
      "score": 0.698,
      "r18": false
    },
    {
      "id": 3480,
      "title": "Sweet 16",
      "score": 0.698,
      "r18": false
    },
    {
      "id": 5333,
      "title": "Miyasaka Kaho Kessakushuu",
      "score": 0.697,
      "r18": false
    }
  ]
}